{
  "run_label": "run-7",
  "v3_url": "https://test4.nick-webdesign.de/",
  "v4_url": "https://test4.nick-webdesign.de/home-v4-atomic-conversion/",
  "mode": "both",
  "section": "all",
  "results": [
    {
      "label": "desktop-fold",
      "mode": "fold",
      "vpLabel": "desktop",
      "numDiff": 1172344,
      "total": 1296000,
      "matchPct": 9.54,
      "passed": false,
      "heightMismatch": false,
      "heightA": 900,
      "heightB": 900,
      "width": 1440,
      "v3PageHeight": 10178,
      "v4PageHeight": 0
    },
    {
      "label": "desktop-full",
      "mode": "full",
      "vpLabel": "desktop",
      "numDiff": 1172345,
      "total": 1296000,
      "matchPct": 9.54,
      "passed": false,
      "heightMismatch": true,
      "heightA": 10178,
      "heightB": 900,
      "width": 1440,
      "v3PageHeight": 10178,
      "v4PageHeight": 0
    },
    {
      "label": "mobile-fold",
      "mode": "fold",
      "vpLabel": "mobile",
      "numDiff": 278008,
      "total": 329160,
      "matchPct": 15.54,
      "passed": false,
      "heightMismatch": false,
      "heightA": 844,
      "heightB": 844,
      "width": 390,
      "v3PageHeight": 14987,
      "v4PageHeight": 0
    },
    {
      "label": "mobile-full",
      "mode": "full",
      "vpLabel": "mobile",
      "numDiff": 278019,
      "total": 329160,
      "matchPct": 15.54,
      "passed": false,
      "heightMismatch": true,
      "heightA": 14987,
      "heightB": 844,
      "width": 390,
      "v3PageHeight": 14987,
      "v4PageHeight": 0
    }
  ],
  "reportPath": "diff-output/report.html"
}
